.travis.yml
README.md
parquet2hive
setup.cfg
setup.py
parquet2hive.egg-info/PKG-INFO
parquet2hive.egg-info/SOURCES.txt
parquet2hive.egg-info/dependency_links.txt
parquet2hive.egg-info/requires.txt
parquet2hive.egg-info/top_level.txt
parquet2hive_modules/__init__.py
parquet2hive_modules/parquet.thrift
parquet2hive_modules/parquet2hivelib.py
parquet2hive_modules/parquet_format/__init__.py
parquet2hive_modules/parquet_format/constants.py
parquet2hive_modules/parquet_format/ttypes.py
tests/complex.parquet
tests/dataset-new.parquet
tests/dataset.parquet
tests/parquet2hive_test.py