Metadata-Version: 1.0
Name: parquet2hive
Version: 0.3.0
Summary: Hive import statement generator for Parquet datasets
Home-page: https://github.com/mozilla/parquet2hive
Author: Roberto Agostino Vitillo
Author-email: rvitillo@mozilla.com
License: UNKNOWN
Platform: UNKNOWN
